{
	"$schema": "https://raw.githubusercontent.com/xen-42/outer-wilds-new-horizons/main/NewHorizons/Schemas/body_schema.json",
	"name": "EXIT",
	"starSystem": "O32.UnnamedMystery",
	"Spawn": {
		"playerSpawn": {
			"startWithSuit": true,
			"position": {
				"x": 100,
				"y": -800,
				"z": 100
			}
		},
		"shipSpawn": {
			"position": {
				"x": 100,
				"y": -805,
				"z": 100
			},
			"rotation": {
				"x": 10,
				"y": 60,
				"z": 20
			}
		}
	},
	"Base": {
		"surfaceSize": 0,
		"surfaceGravity": 0,
		"hasMapMarker": false,
		"showMinimap": false
	},
	"Orbit": {
		"semiMajorAxis": 12000,
		"inclination": 20,
		"primaryBody": "Aetherion",
		"trueAnomaly": 120,
		"isMoon": false,
		"isTidallyLocked": false,
		"axialTilt": -66,
		"longitudeOfAscendingNode": 52,
		"eccentricity": 0,
		"argumentOfPeriapsis": 213,
		"siderealPeriod": 66,
		"showOrbitLine": false
	},
	"ReferenceFrame": {
		"enabled": false
	},
	"ShipLog": {
		"mapMode": {
			"remove": true
		}
	}
}
