{
	"$schema": "https://raw.githubusercontent.com/xen-42/outer-wilds-new-horizons/main/NewHorizons/Schemas/body_schema.json",
	"name": "Metallos",
	"starSystem": "O32.UnnamedMystery",
	"Base": {
		"surfaceSize": 115,
		"surfaceGravity": 6,
		"hasMapMarker": true,
		"showMinimap": true
	},
	"Orbit": {
		"semiMajorAxis": 1300,
		"primaryBody": "Helioraxia",
		"trueAnomaly": 276,
		"isMoon": true,
		"isTidallyLocked": false,
		"siderealPeriod": 5.5,
		"tint": {
			"r": 145,
			"g": 44,
			"b": 0,
			"a": 255
		}
	},
	"HeightMap": {
		"heightMap": "planets/assets/metallos_h.png",
		"textureMap": "planets/assets/metallos_t.png",
		"resolution": 300,
		"minHeight": 55,
		"maxHeight": 65,
		"metallic": 0.9,
		"smoothness": 0.7,
		"normalMap": "planets/assets/metallos_normal.png",
		"baseTile": {
			"textureTile": "planets/assets/tiles/metallos_copper1.png",
			"normalTile": "planets/assets/tiles/metallos_copper2.png",
			"size": 24
		}
	},
	"Volumes": {
		"revealVolumes": [
			{
				"radius": 80,
				"reveals": [ "metallos-fact" ],
				"revealOn": "enter"
			},
			{
				"radius": 5,
				"reveals": [ "spacestation-fact-1" ],
				"revealOn": "enter",
				"position": {
					"x": 5.669589,
					"y": -1.306784,
					"z": -66.7217
				}
			}
		],
		"audioVolumes": [
			{
				"audio": "planets/music/TauxTidalBase.ogg",
				"volume": 0.75,
				"loop": true,
				"track": "music",
				"radius": 115
			}
		]
	},
	"Props": {
		"translatorText": [
			{
				"xmlFile": "planets/xml/tauxNom.xml",
				"type": "recorder",
				"position": {
					"x": 7.59333,
					"y": -3.784699,
					"z": -64.28888
				},
				"rotation": {
					"x": 54.31332,
					"y": 269.8926,
					"z": 96.58382
				}
			},
			{
				"type": "cairnCT",
				"xmlFile": "planets/xml/riddleC.xml",
				"position": {
					"x": 26.21545,
					"y": -21.935,
					"z": -49.22247
				},
				"rotation": {
					"x": 297.3983,
					"y": 89.79083,
					"z": 222.8687
				}
			}
		],
		"details": [
			{
				"assetBundle": "planets/prefabs/o32-unnamedmystery",
				"path": "DynamoLab.prefab",
				"position": {
					"x": 5.076221,
					"y": -0.8978961,
					"z": -60.34192
				},
				"rotation": {
					"x": 86.09605,
					"y": 5.330855,
					"z": 190.7693
				}
			},
			{
				"assetBundle": "planets/prefabs/o32-unnamedmystery",
				"path": "GeothermalLab.prefab",
				"position": {
					"x": 28.10793,
					"y": -6.578366,
					"z": -52.95943
				},
				"rotation": {
					"x": 358.5736,
					"y": 237.2139,
					"z": 92.57935
				}
			},
			{
				"assetBundle": "planets/prefabs/o32-unnamedmystery",
				"path": "GeothermalLab.prefab",
				"position": {
					"x": 29.59102,
					"y": -20.57019,
					"z": -47.13401
				},
				"rotation": {
					"x": 343.7828,
					"y": 228.331,
					"z": 113.5326
				}
			},
			{
				"assetBundle": "planets/prefabs/o32-unnamedmystery",
				"path": "GeothermalLab.prefab",
				"position": {
					"x": 6.440426,
					"y": -28.92404,
					"z": -52.40956
				},
				"rotation": {
					"x": 295.5569,
					"y": 194.1755,
					"z": 160.4697
				}
			},
			{
				"assetBundle": "planets/prefabs/o32-unnamedmystery",
				"path": "GeothermalLab.prefab",
				"position": {
					"x": -15.13049,
					"y": -22.37743,
					"z": -54.90532
				},
				"rotation": {
					"x": 322.1924,
					"y": 119.7764,
					"z": 245.0766
				}
			},
			{
				"assetBundle": "planets/prefabs/o32-unnamedmystery",
				"path": "GeothermalLab.prefab",
				"position": {
					"x": -22.95092,
					"y": -6.301109,
					"z": -56.16106
				},
				"rotation": {
					"x": 26.38635,
					"y": 109.8608,
					"z": 263.7711
				}
			}
		],
		"singularities": [
			{
				"horizonRadius": 0.75,
				"distortRadius": 1.25,
				"type": "blackHole",
				"uniqueID": "spacestation-1",
				"pairedSingularity": "helioplasmia-core",
				"position": {
					"x": 5.669589,
					"y": -1.306784,
					"z": -66.7217
				},
				"rotation": {
					"x": 358.3799,
					"y": 264.9526,
					"z": 93.21265
				}
			}
		]
	},
	"ShipLog": {
		"spriteFolder": "planets/logs/entries/",
		"xmlFile": "planets/logs/metallos.xml",
		"mapMode": {
			"revealedSprite": "planets/logs/mapmode/metallos.png",
			"scale": 0.2,
			"manualPosition": {
				"x": 400,
				"y": -65
			},
			"manualNavigationPosition": {
				"x": 3,
				"y": 1
			}
		}
	}
}